napari_svetlana/CNN2D.py
napari_svetlana/CNN3D.py
napari_svetlana/Config.json
napari_svetlana/CustomDataset.py
napari_svetlana/CustomDialog.py
napari_svetlana/DemoDialog.py
napari_svetlana/Prediction3DDataset.py
napari_svetlana/PredictionDataset.py
napari_svetlana/PredictionMulti3DDataset.py
napari_svetlana/__init__.py
napari_svetlana/_batch_dock_widget.py
napari_svetlana/_dock_widget.py
napari_svetlana/_function.py
napari_svetlana/_reader.py
napari_svetlana/_writer.py
napari_svetlana/debug.py
napari_svetlana/line_length.py
napari_svetlana/mosa.py
napari_svetlana/napari.yaml
napari_svetlana/old_dock_widget.py
napari_svetlana/test_gradcam.py
napari_svetlana/test_gradcam3D.py
napari_svetlana/Grad_Cam/__init__.py
napari_svetlana/Grad_Cam/base_cam.py
napari_svetlana/Grad_Cam/grad_cam.py
napari_svetlana/Grad_Cam/image.py
napari_svetlana/Panuke/filter_labels.py
napari_svetlana/Panuke/generate_labels_file.py
napari_svetlana/Panuke/npy_to_files.py
napari_svetlana/Panuke/npy_to_seg_masks.py
napari_svetlana/Panuke/onehot_to_gt.py
napari_svetlana/Panuke/score_computation.py
napari_svetlana/XP/Predict3Dbatch.py
napari_svetlana/XP/Prediction3DDataset_dilation.py
napari_svetlana/XP/__init__.py
napari_svetlana/XP/compute_accuracy.py
napari_svetlana/XP/extract_save_patches.py
napari_svetlana/XP/modulable_CNN3D.py
napari_svetlana/XP/redim.py
napari_svetlana/XP/reseau.py
napari_svetlana/XP/script_training-stability_test.py
napari_svetlana/XP/script_training_3D_1net.py
napari_svetlana/XP/script_training_3D_dilatation_mask.py
napari_svetlana/XP/script_training_3D_patch_size_norm.py
napari_svetlana/XP/script_training_test.py
napari_svetlana/XP/testeur.py
napari_svetlana/_tests/__init__.py
napari_svetlana/_tests/test_dock_widget.py
napari_svetlana/_tests/test_function.py
napari_svetlana/_tests/test_reader.py
napari_svetlana/_tests/test_writer.py
napari_svetlana/complete_pipeline/Big_template.py
napari_svetlana/complete_pipeline/CNN2D.py
napari_svetlana-1.6.1.dist-info/licenses/LICENSE
napari_svetlana-1.6.1.dist-info/METADATA
napari_svetlana-1.6.1.dist-info/WHEEL
napari_svetlana-1.6.1.dist-info/entry_points.txt
napari_svetlana-1.6.1.dist-info/top_level.txt
napari_svetlana-1.6.1.dist-info/RECORD
