Metadata-Version: 2.4
Name: napari-svetlana
Version: 1.6.1
Summary: A classification plugin for the ROIs of a segmentation mask. If you face problems opening the Napari-hub page, try replacing napari-svetlana by napari_svetlana in the URL.
Author: Clément Cazorla
Author-email: clement.cazorla31@gmail.com
License: GPL-3.0-only
Project-URL: Bug Tracker, https://bitbucket.org/koopa31/napari_svetlana/issues?status=new&status=open
Project-URL: Documentation, https://svetlana-documentation.readthedocs.io/en/latest/
Project-URL: Source Code, https://bitbucket.org/koopa31/napari_svetlana/src/main/
Project-URL: User Support, https://bitbucket.org/koopa31/napari_svetlana/issues?status=new&status=open
Classifier: Development Status :: 2 - Pre-Alpha
Classifier: Intended Audience :: Developers
Classifier: Framework :: napari
Classifier: Topic :: Software Development :: Testing
Classifier: Programming Language :: Python
Classifier: Programming Language :: Python :: 3
Classifier: Programming Language :: Python :: 3.7
Classifier: Programming Language :: Python :: 3.8
Classifier: Programming Language :: Python :: 3.9
Classifier: Operating System :: OS Independent
Classifier: License :: OSI Approved :: GNU General Public License v3 (GPLv3)
Requires-Python: >=3.9
License-File: LICENSE
Requires-Dist: napari-plugin-engine>=0.1.4
Requires-Dist: numpy
Requires-Dist: albumentations==1.0.3
Requires-Dist: joblib==1.2.0
Requires-Dist: light-the-torch
Requires-Dist: matplotlib
Requires-Dist: opencv-python==4.8.1.78
Requires-Dist: pyqtgraph==0.13.3
Requires-Dist: PyQt5
Requires-Dist: cucim==23.10.0; platform_system == "Linux"
Requires-Dist: cupy-cuda115==10.6.0
Requires-Dist: xlsxwriter
Requires-Dist: pandas
Requires-Dist: npe2
Requires-Dist: pooch
Dynamic: license-file
